thaidate/__init__.py
thaidate/thaidate_script.py
thaidate-0.2.5.dist-info/METADATA
thaidate-0.2.5.dist-info/WHEEL
thaidate-0.2.5.dist-info/top_level.txt
thaidate-0.2.5.dist-info/RECORD
