Metadata-Version: 2.1
Name: thaidate
Version: 0.2.5
Summary: python-thaidate
Home-page: UNKNOWN
Author: DewBloodmetal
Author-email: dewscan001@gmail.com
License: UNKNOWN
Keywords: python thaidate python-thaidate
Platform: UNKNOWN
Classifier: Development Status :: 3 - Alpha
Classifier: Programming Language :: Python
Classifier: Programming Language :: Python :: 3.9
